design.sv
module Digital_Clock(
    Clk_1sec,  
    reset,     
    seconds,
    minutes,
    hours);

    input Clk_1sec;  
    input reset;
    output [5:0] seconds;
    output [5:0] minutes;
    output [4:0] hours;
    reg [5:0] seconds;
    reg [5:0] minutes;
    reg [4:0] hours; 

   
    always @(posedge(Clk_1sec) or posedge(reset))
    begin
        if(reset == 1'b1) begin  
            seconds = 0;
            minutes = 0;
            hours = 0;  end
        else if(Clk_1sec == 1'b1) begin 
            seconds = seconds + 1; 
            if(seconds == 60) begin
                seconds = 0;  
                minutes = minutes + 1; 
                if(minutes == 60) begin 
                    minutes = 0;  
                    hours = hours + 1;  
                   if(hours ==  24) begin  
                        hours = 0; 
                    end 
                end
            end     
        end
    end     

endmodule

module bcd_to_7seg_display (
    input clk,
    input reset,
    input [15:0] bcd_data,
    output reg [6:0] seg,
    output reg [3:0] an
);
    reg [1:0] digit_select = 0;
    reg [15:0] refresh_counter = 0;
    reg [3:0] current_bcd;

    wire refresh_tick = (refresh_counter == 49999);

    always @(posedge clk or posedge reset) begin
        if (reset) begin
            refresh_counter <= 0;
            digit_select <= 0;
        end else if (refresh_tick) begin
            refresh_counter <= 0;
            digit_select <= digit_select + 1;
        end else begin
            refresh_counter <= refresh_counter + 1;
        end
    end

    always @(*) begin
        case (digit_select)
            2'b00: begin current_bcd = bcd_data[3:0];   an = 4'b1110; end
            2'b01: begin current_bcd = bcd_data[7:4];   an = 4'b1101; end
            2'b10: begin current_bcd = bcd_data[11:8];  an = 4'b1011; end
            2'b11: begin current_bcd = bcd_data[15:12]; an = 4'b0111; end
        endcase
    end

    always @(*) begin
        case (current_bcd)
            4'd0: seg = 7'b1111110;
            4'd1: seg = 7'b0110000;
            4'd2: seg = 7'b1101101;
            4'd3: seg = 7'b1111001;
            4'd4: seg = 7'b0110011;
            4'd5: seg = 7'b1011011;
            4'd6: seg = 7'b1011111;
            4'd7: seg = 7'b1110000;
            4'd8: seg = 7'b1111111;
            4'd9: seg = 7'b1111011;
            default: seg = 7'b0000001;
        endcase
    end
endmodule

testbench.sv
module tb_clock;

    
    reg Clk_1sec;
    reg reset;

    wire [5:0] seconds;
    wire [5:0] minutes;
    wire [4:0] hours;
  wire blink_led;
  wire [6:0] seg_min, seg_hr;
  wire [3:0] an_min, an_hr;

    Digital_Clock uut (
        .Clk_1sec(Clk_1sec), 
        .reset(reset), 
        .seconds(seconds), 
        .minutes(minutes), 
        .hours(hours)
    );
  assign blink_led = seconds[0]; 
  wire [3:0] min_units = minutes % 10;
  wire [3:0] min_tens = minutes / 10;
  wire [3:0] hr_units = hours% 10;
  wire [3:00] hr_tens = hours / 10;
  
  bcd_to_7seg_display min_display (.clk(Clk_1sec), .reset(reset), .bcd_data({4'b0000, 4'b0000, hr_tens, hr_units}), .seg(seg_hr), .an(an_hr));
  
    
    initial Clk_1sec = 0;
    always #500 Clk_1sec = ~Clk_1sec;  
    initial begin
      $dumpfile("Digital_Clock.vcd");
      $dumpvars;
      $monitor("Time:%0t | H:%0d M:%0d S:%0d", $time, hours, minutes, seconds, blink_led);
        reset = 1;
       
        #100;
        reset = 0;  
      #50000;
      $finish;
      
    end
      
endmodule

Digital_Clock.vcd
$date
	Sun Jul 13 10:13:45 2025
$end
$version
	Icarus Verilog
$end
$timescale
	1s
$end
$scope module tb_clock $end
$var wire 7 ! seg_hr [6:0] $end
$var wire 6 " seconds [5:0] $end
$var wire 6 # minutes [5:0] $end
$var wire 4 $ min_units [3:0] $end
$var wire 4 % min_tens [3:0] $end
$var wire 4 & hr_units [3:0] $end
$var wire 4 ' hr_tens [3:0] $end
$var wire 5 ( hours [4:0] $end
$var wire 1 ) blink_led $end
$var wire 4 * an_hr [3:0] $end
$var reg 1 + Clk_1sec $end
$var reg 1 , reset $end
$scope module min_display $end
$var wire 16 - bcd_data [15:0] $end
$var wire 1 + clk $end
$var wire 1 , reset $end
$var wire 1 . refresh_tick $end
$var reg 4 / an [3:0] $end
$var reg 4 0 current_bcd [3:0] $end
$var reg 2 1 digit_select [1:0] $end
$var reg 16 2 refresh_counter [15:0] $end
$var reg 7 3 seg [6:0] $end
$upscope $end
$scope module uut $end
$var wire 1 + Clk_1sec $end
$var wire 1 , reset $end
$var reg 5 4 hours [4:0] $end
$var reg 6 5 minutes [5:0] $end
$var reg 6 6 seconds [5:0] $end
$upscope $end
$upscope $end
$enddefinitions $end
$comment Show the parameter values. $end
$dumpall
$end
#0
$dumpvars
b0 6
b0 5
b0 4
b1111110 3
b0 2
b0 1
b0 0
b1110 /
0.
b0 -
1,
0+
b1110 *
0)
b0 (
b0 '
b0 &
b0 %
b0 $
b0 #
b0 "
b1111110 !
$end
#100
0,
#500
b1 2
1)
b1 "
b1 6
1+
#1000
0+
#1500
b10 2
0)
b10 "
b10 6
1+
#2000
0+
#2500
b11 2
1)
b11 "
b11 6
1+
#3000
0+
#3500
b100 2
0)
b100 "
b100 6
1+
#4000
0+
#4500
b101 2
1)
b101 "
b101 6
1+
#5000
0+
#5500
b110 2
0)
b110 "
b110 6
1+
#6000
0+
#6500
b111 2
1)
b111 "
b111 6
1+
#7000
0+
#7500
b1000 2
0)
b1000 "
b1000 6
1+
#8000
0+
#8500
b1001 2
1)
b1001 "
b1001 6
1+
#9000
0+
#9500
b1010 2
0)
b1010 "
b1010 6
1+
#10000
0+
#10500
b1011 2
1)
b1011 "
b1011 6
1+
#11000
0+
#11500
b1100 2
0)
b1100 "
b1100 6
1+
#12000
0+
#12500
b1101 2
1)
b1101 "
b1101 6
1+
#13000
0+
#13500
b1110 2
0)
b1110 "
b1110 6
1+
#14000
0+
#14500
b1111 2
1)
b1111 "
b1111 6
1+
#15000
0+
#15500
b10000 2
0)
b10000 "
b10000 6
1+
#16000
0+
#16500
b10001 2
1)
b10001 "
b10001 6
1+
#17000
0+
#17500
b10010 2
0)
b10010 "
b10010 6
1+
#18000
0+
#18500
b10011 2
1)
b10011 "
b10011 6
1+
#19000
0+
#19500
b10100 2
0)
b10100 "
b10100 6
1+
#20000
0+
#20500
b10101 2
1)
b10101 "
b10101 6
1+
#21000
0+
#21500
b10110 2
0)
b10110 "
b10110 6
1+
#22000
0+
#22500
b10111 2
1)
b10111 "
b10111 6
1+
#23000
0+
#23500
b11000 2
0)
b11000 "
b11000 6
1+
#24000
0+
#24500
b11001 2
1)
b11001 "
b11001 6
1+
#25000
0+
#25500
b11010 2
0)
b11010 "
b11010 6
1+
#26000
0+
#26500
b11011 2
1)
b11011 "
b11011 6
1+
#27000
0+
#27500
b11100 2
0)
b11100 "
b11100 6
1+
#28000
0+
#28500
b11101 2
1)
b11101 "
b11101 6
1+
#29000
0+
#29500
b11110 2
0)
b11110 "
b11110 6
1+
#30000
0+
#30500
b11111 2
1)
b11111 "
b11111 6
1+
#31000
0+
#31500
b100000 2
0)
b100000 "
b100000 6
1+
#32000
0+
#32500
b100001 2
1)
b100001 "
b100001 6
1+
#33000
0+
#33500
b100010 2
0)
b100010 "
b100010 6
1+
#34000
0+
#34500
b100011 2
1)
b100011 "
b100011 6
1+
#35000
0+
#35500
b100100 2
0)
b100100 "
b100100 6
1+
#36000
0+
#36500
b100101 2
1)
b100101 "
b100101 6
1+
#37000
0+
#37500
b100110 2
0)
b100110 "
b100110 6
1+
#38000
0+
#38500
b100111 2
1)
b100111 "
b100111 6
1+
#39000
0+
#39500
b101000 2
0)
b101000 "
b101000 6
1+
#40000
0+
#40500
b101001 2
1)
b101001 "
b101001 6
1+
#41000
0+
#41500
b101010 2
0)
b101010 "
b101010 6
1+
#42000
0+
#42500
b101011 2
1)
b101011 "
b101011 6
1+
#43000
0+
#43500
b101100 2
0)
b101100 "
b101100 6
1+
#44000
0+
#44500
b101101 2
1)
b101101 "
b101101 6
1+
#45000
0+
#45500
b101110 2
0)
b101110 "
b101110 6
1+
#46000
0+
#46500
b101111 2
1)
b101111 "
b101111 6
1+
#47000
0+
#47500
b110000 2
0)
b110000 "
b110000 6
1+
#48000
0+
#48500
b110001 2
1)
b110001 "
b110001 6
1+
#49000
0+
#49500
b110010 2
0)
b110010 "
b110010 6
1+
